collector/__init__.py
collector/collect.py
nca/SchemeRunner.py
nca/VERSION.txt
nca/__init__.py
nca/__main__.py
nca/nca_cli.py
nca/CoreDS/CanonicalHyperCubeSet.py
nca/CoreDS/CanonicalIntervalSet.py
nca/CoreDS/ConnectivityCube.py
nca/CoreDS/ConnectivityProperties.py
nca/CoreDS/DimensionsManager.py
nca/CoreDS/MethodSet.py
nca/CoreDS/MinDFA.py
nca/CoreDS/Peer.py
nca/CoreDS/PortSet.py
nca/CoreDS/ProtocolNameResolver.py
nca/CoreDS/ProtocolSet.py
nca/CoreDS/__init__.py
nca/FWRules/ClusterInfo.py
nca/FWRules/ConnectivityGraph.py
nca/FWRules/DotGraph.py
nca/FWRules/FWRule.py
nca/FWRules/InteractiveConnectivityGraph.py
nca/FWRules/MinimizeCsFWRules.py
nca/FWRules/MinimizeFWRules.py
nca/FWRules/__init__.py
nca/FWRules/interactiveJsCode.js
nca/FileScanners/DirScanner.py
nca/FileScanners/GenericTreeScanner.py
nca/FileScanners/GitScanner.py
nca/FileScanners/HelmScanner.py
nca/FileScanners/__init__.py
nca/NetworkConfig/NetworkConfig.py
nca/NetworkConfig/NetworkConfigQuery.py
nca/NetworkConfig/NetworkConfigQueryRunner.py
nca/NetworkConfig/NetworkLayer.py
nca/NetworkConfig/PeerContainer.py
nca/NetworkConfig/PoliciesFinder.py
nca/NetworkConfig/QueryOutputHandler.py
nca/NetworkConfig/ResourcesHandler.py
nca/NetworkConfig/TopologyObjectsFinder.py
nca/NetworkConfig/__init__.py
nca/NetworkConfig/LiveSim/dns/dns_pods.yaml
nca/NetworkConfig/LiveSim/ingress_controller/ingress_controller.yaml
nca/NetworkConfig/LiveSim/istio_gateway/istio_custom_gateway.yaml
nca/NetworkConfig/LiveSim/istio_gateway/istio_egress_gateway.yaml
nca/NetworkConfig/LiveSim/istio_gateway/istio_ingress_gateway.yaml
nca/Parsers/CalicoPolicyYamlParser.py
nca/Parsers/GenericGatewayYamlParser.py
nca/Parsers/GenericYamlParser.py
nca/Parsers/IngressPolicyYamlParser.py
nca/Parsers/IstioGatewayPolicyGenerator.py
nca/Parsers/IstioGatewayYamlParser.py
nca/Parsers/IstioGenericYamlParser.py
nca/Parsers/IstioPolicyYamlParser.py
nca/Parsers/IstioServiceEntryYamlParser.py
nca/Parsers/IstioSidecarYamlParser.py
network_config_analyzer-2.1.0.dist-info/LICENSE
network_config_analyzer-2.1.0.dist-info/METADATA
network_config_analyzer-2.1.0.dist-info/WHEEL
network_config_analyzer-2.1.0.dist-info/entry_points.txt
network_config_analyzer-2.1.0.dist-info/top_level.txt
network_config_analyzer-2.1.0.dist-info/RECORD
