Metadata-Version: 2.1
Name: network-config-analyzer
Version: 2.1.0
Summary: An analyzer for Network Policies and other connectivity-configuration resources
Home-page: https://github.com/np-guard/network-config-analyzer
Author: Ziv Nevo
Author-email: nevo@il.ibm.com
Project-URL: Bug Tracker, https://github.com/np-guard/network-config-analyzer/issues
Project-URL: NP-Guard Home, https://np-guard.github.io
Classifier: Programming Language :: Python :: 3
Classifier: License :: OSI Approved :: Apache Software License
Classifier: Operating System :: OS Independent
Requires-Python: >=3.9
License-File: LICENSE
Requires-Dist: ghapi==1.0.6
Requires-Dist: PyYAML==6.0.2
Requires-Dist: greenery==4.0.0
Requires-Dist: networkx==3.2.1
Requires-Dist: beautifulsoup4==4.12.3
Requires-Dist: lxml==5.3.0
